pyDEW/DEW2019.pkl
pyDEW/DEW2019_oldTE.pkl
pyDEW/__init__.py
pyDEW/core.py
pyDEW/defaultsystem.py
pyDEW/dewminerals.pkl
pyDEW/dewminerals_oldTE.pkl
pyDEW/eq6_output.py
pyDEW/fluid.py
pyDEW/output.py
pyDEW/reaction.py
pyDEW/robieref.py
pyDEW/system.py
pyDEW/dew2019_coderfiles/AGCL2_n_dew2019_calc.c
pyDEW/dew2019_coderfiles/AGCL2_n_dew2019_calc.h
pyDEW/dew2019_coderfiles/AGCL_l_AQ_r__dew2019_calc.c
pyDEW/dew2019_coderfiles/AGCL_l_AQ_r__dew2019_calc.h
pyDEW/dew2019_coderfiles/AG_p_dew2019_calc.c
pyDEW/dew2019_coderfiles/AG_p_dew2019_calc.h
pyDEW/dew2019_coderfiles/AL_l_OH_r_3_l_AQ_r__dew2019_calc.c
pyDEW/dew2019_coderfiles/AL_l_OH_r_3_l_AQ_r__dew2019_calc.h
pyDEW/dew2019_coderfiles/AL_l_OH_r_4_n_dew2019_calc.c
pyDEW/dew2019_coderfiles/AL_l_OH_r_4_n_dew2019_calc.h
pyDEW/dew2019_coderfiles/AL_l_OH_r_SI_l_OH_r__n_dew2019_calc.c
pyDEW/dew2019_coderfiles/AL_l_OH_r_SI_l_OH_r__n_dew2019_calc.h
pyDEW/dew2019_coderfiles/AL_p3_dew2019_calc.c
pyDEW/dew2019_coderfiles/AL_p3_dew2019_calc.h
pyDEW/dew2019_coderfiles/AR_l_AQ_r__dew2019_calc.c
pyDEW/dew2019_coderfiles/AR_l_AQ_r__dew2019_calc.h
pyDEW/dew2019_coderfiles/AU_p3_dew2019_calc.c
pyDEW/dew2019_coderfiles/AU_p3_dew2019_calc.h
pyDEW/dew2019_coderfiles/AU_p_dew2019_calc.c
pyDEW/dew2019_coderfiles/AU_p_dew2019_calc.h
pyDEW/dew2019_coderfiles/BACL_p_dew2019_calc.c
pyDEW/dew2019_coderfiles/BACL_p_dew2019_calc.h
pyDEW/dew2019_coderfiles/BA_p2_dew2019_calc.c
pyDEW/dew2019_coderfiles/BA_p2_dew2019_calc.h
pyDEW/dew2019_coderfiles/BENZENE_l_AQ_r__dew2019_calc.c
pyDEW/dew2019_coderfiles/BENZENE_l_AQ_r__dew2019_calc.h
pyDEW/dew2019_coderfiles/BE_p2_dew2019_calc.c
pyDEW/dew2019_coderfiles/BE_p2_dew2019_calc.h
pyDEW/dew2019_coderfiles/BO2_n_dew2019_calc.c
pyDEW/dew2019_coderfiles/BO2_n_dew2019_calc.h
pyDEW/dew2019_coderfiles/BO_l_OH_r__l_AQ_r__dew2019_calc.c
pyDEW/dew2019_coderfiles/BO_l_OH_r__l_AQ_r__dew2019_calc.h
pyDEW/dew2019_coderfiles/BR_n_dew2019_calc.c
pyDEW/dew2019_coderfiles/BR_n_dew2019_calc.h
pyDEW-0.14.dist-info/LICENSE
pyDEW-0.14.dist-info/METADATA
pyDEW-0.14.dist-info/WHEEL
pyDEW-0.14.dist-info/top_level.txt
pyDEW-0.14.dist-info/RECORD
